{
	"fetched": 16,
	"records": [
		{
			"attributes": {
				"type": "Event__c",
				"url": "/services/data/v57.0/sobjects/Event__c/a02DC00000GedNwYAJ"
			},
			"ActiveEvent__c": true,
			"Id": "a02DC00000GedNwYAJ",
			"Name": "Salesforce Development (SFDX, VS Code, etc)",
			"Order__c": 0.5
		},
		{
			"attributes": {
				"type": "Event__c",
				"url": "/services/data/v57.0/sobjects/Event__c/a02DC00000GedNtYAJ"
			},
			"ActiveEvent__c": true,
			"Id": "a02DC00000GedNtYAJ",
			"Name": "2023.03 - TrailblazerDX 23",
			"Order__c": 1
		},
		{
			"attributes": {
				"type": "Event__c",
				"url": "/services/data/v57.0/sobjects/Event__c/a02DC00000GedNxYAJ"
			},
			"ActiveEvent__c": true,
			"Id": "a02DC00000GedNxYAJ",
			"Name": "Install LWC_HOW",
			"Order__c": 2
		},
		{
			"attributes": {
				"type": "Event__c",
				"url": "/services/data/v57.0/sobjects/Event__c/a02DC00000GedNuYAJ"
			},
			"ActiveEvent__c": true,
			"Id": "a02DC00000GedNuYAJ",
			"Name": "_Salesforce Fonts_",
			"Order__c": 20
		},
		{
			"attributes": {
				"type": "Event__c",
				"url": "/services/data/v57.0/sobjects/Event__c/a02DC00000GedNvYAJ"
			},
			"ActiveEvent__c": true,
			"Id": "a02DC00000GedNvYAJ",
			"Name": "_Manual Checks_",
			"Order__c": 21
		},
		{
			"attributes": {
				"type": "Event__c",
				"url": "/services/data/v57.0/sobjects/Event__c/a02DC00000GedO1YAJ"
			},
			"ActiveEvent__c": false,
			"Id": "a02DC00000GedO1YAJ",
			"Name": "_Logout from student Apps",
			"Order__c": 22
		},
		{
			"attributes": {
				"type": "Event__c",
				"url": "/services/data/v57.0/sobjects/Event__c/a02DC00000GedNyYAJ"
			},
			"ActiveEvent__c": false,
			"Id": "a02DC00000GedNyYAJ",
			"Name": "ET_EPL - Start on crash or reboot",
			"Order__c": 50
		},
		{
			"attributes": {
				"type": "Event__c",
				"url": "/services/data/v57.0/sobjects/Event__c/a02DC00000GedNzYAJ"
			},
			"ActiveEvent__c": false,
			"Id": "a02DC00000GedNzYAJ",
			"Name": "ET_EPL - KILL ETEPL",
			"Order__c": 51
		},
		{
			"attributes": {
				"type": "Event__c",
				"url": "/services/data/v57.0/sobjects/Event__c/a02DC00000GedO0YAJ"
			},
			"ActiveEvent__c": false,
			"Id": "a02DC00000GedO0YAJ",
			"Name": "ET_EPL - _Re-Install Event Proctor Login_",
			"Order__c": 53
		},
		{
			"attributes": {
				"type": "Event__c",
				"url": "/services/data/v57.0/sobjects/Event__c/a02DC00000GedO2YAJ"
			},
			"ActiveEvent__c": false,
			"Id": "a02DC00000GedO2YAJ",
			"Name": "ET_EPL - DO NOT USE -- Kill Event Proctor Login",
			"Order__c": 99
		},
		{
			"attributes": {
				"type": "Event__c",
				"url": "/services/data/v57.0/sobjects/Event__c/a02DC00000GedO3YAJ"
			},
			"ActiveEvent__c": false,
			"Id": "a02DC00000GedO3YAJ",
			"Name": "2019.05 - TDX '19 - HOWs",
			"Order__c": 100
		},
		{
			"attributes": {
				"type": "Event__c",
				"url": "/services/data/v57.0/sobjects/Event__c/a02DC00000GedO4YAJ"
			},
			"ActiveEvent__c": false,
			"Id": "a02DC00000GedO4YAJ",
			"Name": "2019.05 - TDX '19 - Bootcamp",
			"Order__c": 101
		},
		{
			"attributes": {
				"type": "Event__c",
				"url": "/services/data/v57.0/sobjects/Event__c/a02DC00000GedO5YAJ"
			},
			"ActiveEvent__c": false,
			"Id": "a02DC00000GedO5YAJ",
			"Name": "2019.12 - India TDX '19",
			"Order__c": 102
		},
		{
			"attributes": {
				"type": "Event__c",
				"url": "/services/data/v57.0/sobjects/Event__c/a02DC00000GedO6YAJ"
			},
			"ActiveEvent__c": false,
			"Id": "a02DC00000GedO6YAJ",
			"Name": "2022.04 - TrailblazerDX 22",
			"Order__c": 103
		},
		{
			"attributes": {
				"type": "Event__c",
				"url": "/services/data/v57.0/sobjects/Event__c/a02DC00000GedO7YAJ"
			},
			"ActiveEvent__c": false,
			"Id": "a02DC00000GedO7YAJ",
			"Name": "2022.09 - Dreamforce22",
			"Order__c": 104
		},
		{
			"attributes": {
				"type": "Event__c",
				"url": "/services/data/v57.0/sobjects/Event__c/a02DC00000GedO8YAJ"
			},
			"ActiveEvent__c": true,
			"Id": "a02DC00000GedO8YAJ",
			"Name": "__OLD ACTIONS",
			"Order__c": 899
		}
	],
	"total": 16
}