{
	"fetched": 16,
	"records": [
		{
			"attributes": {
				"type": "Event__c",
				"url": "/services/data/v57.0/sobjects/Event__c/a0203000002tNW0AAM"
			},
			"ActiveEvent__c": true,
			"Id": "a0203000002tNW0AAM",
			"Name": "2023.03 - TrailblazerDX 23",
			"Order__c": 1
		},
		{
			"attributes": {
				"type": "Event__c",
				"url": "/services/data/v57.0/sobjects/Event__c/a0203000002tNW1AAM"
			},
			"ActiveEvent__c": true,
			"Id": "a0203000002tNW1AAM",
			"Name": "_Salesforce Fonts_",
			"Order__c": 20
		},
		{
			"attributes": {
				"type": "Event__c",
				"url": "/services/data/v57.0/sobjects/Event__c/a0203000002tNW2AAM"
			},
			"ActiveEvent__c": true,
			"Id": "a0203000002tNW2AAM",
			"Name": "_Manual Checks_",
			"Order__c": 21
		},
		{
			"attributes": {
				"type": "Event__c",
				"url": "/services/data/v57.0/sobjects/Event__c/a0203000002tNW3AAM"
			},
			"ActiveEvent__c": true,
			"Id": "a0203000002tNW3AAM",
			"Name": "_Salesforce Development (SFDX, VS Code, etc)_",
			"Order__c": 22
		},
		{
			"attributes": {
				"type": "Event__c",
				"url": "/services/data/v57.0/sobjects/Event__c/a0203000002tNW4AAM"
			},
			"ActiveEvent__c": true,
			"Id": "a0203000002tNW4AAM",
			"Name": "_Install LWC_HOW",
			"Order__c": 23
		},
		{
			"attributes": {
				"type": "Event__c",
				"url": "/services/data/v57.0/sobjects/Event__c/a0203000002tNW5AAM"
			},
			"ActiveEvent__c": true,
			"Id": "a0203000002tNW5AAM",
			"Name": "ET_EPL - Start on crash or reboot",
			"Order__c": 50
		},
		{
			"attributes": {
				"type": "Event__c",
				"url": "/services/data/v57.0/sobjects/Event__c/a0203000002tNW6AAM"
			},
			"ActiveEvent__c": true,
			"Id": "a0203000002tNW6AAM",
			"Name": "ET_EPL - KILL ETEPL",
			"Order__c": 51
		},
		{
			"attributes": {
				"type": "Event__c",
				"url": "/services/data/v57.0/sobjects/Event__c/a0203000002tNW7AAM"
			},
			"ActiveEvent__c": true,
			"Id": "a0203000002tNW7AAM",
			"Name": "ET_EPL - _Re-Install Event Proctor Login_",
			"Order__c": 53
		},
		{
			"attributes": {
				"type": "Event__c",
				"url": "/services/data/v57.0/sobjects/Event__c/a0203000002tNW8AAM"
			},
			"ActiveEvent__c": true,
			"Id": "a0203000002tNW8AAM",
			"Name": "Logout from student Apps",
			"Order__c": 54
		},
		{
			"attributes": {
				"type": "Event__c",
				"url": "/services/data/v57.0/sobjects/Event__c/a0203000002tNW9AAM"
			},
			"ActiveEvent__c": true,
			"Id": "a0203000002tNW9AAM",
			"Name": "ET_EPL - DO NOT USE -- Kill Event Proctor Login",
			"Order__c": 99
		},
		{
			"attributes": {
				"type": "Event__c",
				"url": "/services/data/v57.0/sobjects/Event__c/a0203000002tNWAAA2"
			},
			"ActiveEvent__c": false,
			"Id": "a0203000002tNWAAA2",
			"Name": "2019.05 - TDX '19 - HOWs",
			"Order__c": 100
		},
		{
			"attributes": {
				"type": "Event__c",
				"url": "/services/data/v57.0/sobjects/Event__c/a0203000002tNWBAA2"
			},
			"ActiveEvent__c": false,
			"Id": "a0203000002tNWBAA2",
			"Name": "2019.05 - TDX '19 - Bootcamp",
			"Order__c": 101
		},
		{
			"attributes": {
				"type": "Event__c",
				"url": "/services/data/v57.0/sobjects/Event__c/a0203000002tNWCAA2"
			},
			"ActiveEvent__c": false,
			"Id": "a0203000002tNWCAA2",
			"Name": "2019.12 - India TDX '19",
			"Order__c": 102
		},
		{
			"attributes": {
				"type": "Event__c",
				"url": "/services/data/v57.0/sobjects/Event__c/a0203000002tNWDAA2"
			},
			"ActiveEvent__c": false,
			"Id": "a0203000002tNWDAA2",
			"Name": "2022.04 - TrailblazerDX 22",
			"Order__c": 103
		},
		{
			"attributes": {
				"type": "Event__c",
				"url": "/services/data/v57.0/sobjects/Event__c/a0203000002tNWEAA2"
			},
			"ActiveEvent__c": false,
			"Id": "a0203000002tNWEAA2",
			"Name": "2022.09 - Dreamforce22",
			"Order__c": 104
		},
		{
			"attributes": {
				"type": "Event__c",
				"url": "/services/data/v57.0/sobjects/Event__c/a0203000002tNWFAA2"
			},
			"ActiveEvent__c": false,
			"Id": "a0203000002tNWFAA2",
			"Name": "__OLD ACTIONS",
			"Order__c": 899
		}
	],
	"total": 16
}